botbuilder/integration/applicationinsights/aiohttp/__init__.py
botbuilder/integration/applicationinsights/aiohttp/about.py
botbuilder/integration/applicationinsights/aiohttp/aiohttp_telemetry_middleware.py
botbuilder/integration/applicationinsights/aiohttp/aiohttp_telemetry_processor.py
botbuilder_integration_applicationinsights_aiohttp-4.17.1.dist-info/METADATA
botbuilder_integration_applicationinsights_aiohttp-4.17.1.dist-info/WHEEL
botbuilder_integration_applicationinsights_aiohttp-4.17.1.dist-info/top_level.txt
botbuilder_integration_applicationinsights_aiohttp-4.17.1.dist-info/RECORD
